dbt_toolbox/__init__.py
dbt_toolbox/constants.py
dbt_toolbox/data_models.py
dbt_toolbox/run_config.py
dbt_toolbox/settings.py
dbt_toolbox/warnings_collector.py
dbt_toolbox/actions/all_settings.py
dbt_toolbox/actions/build_docs.py
dbt_toolbox/actions/dbt_executor.py
dbt_toolbox/analysees/__init__.py
dbt_toolbox/analysees/columns.py
dbt_toolbox/analysees/data_models.py
dbt_toolbox/analysees/docs_macros.py
dbt_toolbox/analysees/models.py
dbt_toolbox/analysees/print_analysis.py
dbt_toolbox/cli/__init__.py
dbt_toolbox/cli/_build_run_command_factory.py
dbt_toolbox/cli/_common_options.py
dbt_toolbox/cli/_dbt_output_parser.py
dbt_toolbox/cli/_exit_handler.py
dbt_toolbox/cli/analyze.py
dbt_toolbox/cli/build.py
dbt_toolbox/cli/clean.py
dbt_toolbox/cli/docs.py
dbt_toolbox/cli/main.py
dbt_toolbox/cli/run.py
dbt_toolbox/cli/settings.py
dbt_toolbox/dbt_parser/__init__.py
dbt_toolbox/dbt_parser/_builders.py
dbt_toolbox/dbt_parser/_cache.py
dbt_toolbox/dbt_parser/_column_resolver.py
dbt_toolbox/dbt_parser/_dbt_parser.py
dbt_toolbox/dbt_parser/_file_fetcher.py
dbt_toolbox/dbt_parser/_jinja_handler.py
dbt_toolbox/dbt_parser/_selection_parser.py
dbt_toolbox/graph/__init__.py
dbt_toolbox/graph/dependency_graph.py
dbt_toolbox/mcp/__init__.py
dbt_toolbox/mcp/_utils.py
dbt_toolbox/mcp/mcp.py
dbt_toolbox/mcp/tool_analyze_models.py
dbt_toolbox/mcp/tool_build_model.py
dbt_toolbox/mcp/tool_generate_docs.py
dbt_toolbox/mcp/tool_list_dbt_objects.py
dbt_toolbox/mcp/tool_show_docs.py
dbt_toolbox/testing/__init__.py
dbt_toolbox/testing/column_tests.py
dbt_toolbox/utils/__init__.py
dbt_toolbox/utils/_paths.py
dbt_toolbox/utils/_printers.py
dbt_toolbox/utils/dict_utils.py
dbt_toolbox-0.8.1.dist-info/METADATA
dbt_toolbox-0.8.1.dist-info/WHEEL
dbt_toolbox-0.8.1.dist-info/entry_points.txt
dbt_toolbox-0.8.1.dist-info/licenses/LICENSE
dbt_toolbox-0.8.1.dist-info/RECORD
