Metadata-Version: 2.4
Name: dbt-toolbox
Version: 0.8.1
Summary: Productivity, warehous cost and QoL improvements for your dbt development
Project-URL: Homepage, https://github.com/erikmunkby/dbt-toolbox
Project-URL: Documentation, https://github.com/erikmunkby/dbt-toolbox/blob/main/CLI.md
Project-URL: Repository, https://github.com/erikmunkby/dbt-toolbox
Project-URL: Issues, https://github.com/erikmunkby/dbt-toolbox/issues
Author-email: Erik Munkby <erik.munkby@gmail.com>
License: MIT License
License-File: LICENSE
Requires-Python: >=3.10
Requires-Dist: jinja2>=3.1.6
Requires-Dist: loguru>=0.7.3
Requires-Dist: rapidfuzz>=3.14.3
Requires-Dist: sqlglot[rs]>=26.25.3
Requires-Dist: tomli>=2.2.1
Requires-Dist: typer>=0.16.0
Requires-Dist: yamlium>=0.1.4
Provides-Extra: mcp
Requires-Dist: fastmcp>=2.11.3; extra == 'mcp'
